gaws/__init__.py
gaws/__main__.py
GAWS-0.10.3.dist-info/LICENSE
GAWS-0.10.3.dist-info/METADATA
GAWS-0.10.3.dist-info/WHEEL
GAWS-0.10.3.dist-info/entry_points.txt
GAWS-0.10.3.dist-info/top_level.txt
GAWS-0.10.3.dist-info/RECORD
