Metadata-Version: 2.1
Name: GAWS
Version: 0.10.3
Summary: Google Amazon Wrapper Single sign on
Home-page: UNKNOWN
Author: Daniel Ripoll
Author-email: info@danielripoll.es
License: BSD
Project-URL: Code, https://github.com/JustDevZero/GAWS
Project-URL: Issue tracker, https://github.com/JustDevZero/GAWS
Keywords: google,aws,wrapper,single-sign-on
Platform: Linux
Platform: macOS
Platform: Windows
Classifier: Development Status :: 5 - Production/Stable
Classifier: Intended Audience :: Developers
Classifier: Intended Audience :: System Administrators
Classifier: License :: OSI Approved :: BSD License
Classifier: Programming Language :: Python :: 3
Classifier: Programming Language :: Python :: 3.6
Classifier: Programming Language :: Python :: 3.7
Classifier: Programming Language :: Python :: 3.8
Classifier: Programming Language :: Python :: 3.9
Classifier: Topic :: Utilities
Classifier: Topic :: System
Classifier: Topic :: System :: Installation/Setup
Requires-Python: >=3.6
Requires-Dist: aws-google-auth (~=0.0.37)
Requires-Dist: boto3 (~=1.19.12)
Requires-Dist: odfpy (~=1.4.1)
Requires-Dist: openpyxl (~=3.0.9)
Requires-Dist: xlwt (~=1.3.0)
